polychromy/__init__.py
polychromy/polychromy.py
polychromy/data/colors.json
polychromy-1.1.1.dist-info/licenses/LICENSE.md
polychromy-1.1.1.dist-info/METADATA
polychromy-1.1.1.dist-info/WHEEL
polychromy-1.1.1.dist-info/top_level.txt
polychromy-1.1.1.dist-info/RECORD
