Metadata-Version: 2.4
Name: polychromy
Version: 1.1.1
Summary: A module to print strings in a given colour, with a given colour background
Author-email: scalvaruso <calvaruso.simone@gmail.com>
License: MIT License
Project-URL: Homepage, https://pypi.org/project/polychromy
Project-URL: Repository, https://github.com/scalvaruso/polychromy
Project-URL: Issues, https://github.com/scalvaruso/polychromy/issues
Keywords: ansi,background,color,colour,colorate,font,format,foreground,Hex,paint,RGB,sRGB,text
Classifier: Programming Language :: Python :: 3
Classifier: Programming Language :: Python :: 3.9
Classifier: Programming Language :: Python :: 3.10
Classifier: Programming Language :: Python :: 3.11
Classifier: License :: OSI Approved :: MIT License
Classifier: Operating System :: OS Independent
Requires-Python: >=3.9
License-File: LICENSE.md
Requires-Dist: textlinebreaker>=1.0.0
Requires-Dist: requests
Dynamic: license-file
Dynamic: requires-python
